sphinx_better_subsection.py
sphinx_better_subsection-0.2.dist-info/METADATA
sphinx_better_subsection-0.2.dist-info/WHEEL
sphinx_better_subsection-0.2.dist-info/entry_points.txt
sphinx_better_subsection-0.2.dist-info/license_files/LICENSE
sphinx_better_subsection-0.2.dist-info/RECORD
