Metadata-Version: 2.1
Name: sphinx-better-subsection
Version: 0.2
Summary: Better your Sphinx section IDs
Project-URL: Homepage, https://github.com/GeeTransit/sphinx-better-subsection
Author-email: George Zhang <geetransit@gmail.com>
License: MIT
Classifier: Development Status :: 3 - Alpha
Classifier: Framework :: Sphinx :: Extension
Classifier: License :: OSI Approved :: MIT License
Classifier: Operating System :: OS Independent
Classifier: Programming Language :: Python :: 3
Requires-Python: >=3.7
Requires-Dist: docutils>=0.14
